hl_gaming_official_ff_data/__init__.py
hl_gaming_official_ff_data/client.py
hl_gaming_official_ff_data-2.3.9.dist-info/METADATA
hl_gaming_official_ff_data-2.3.9.dist-info/WHEEL
hl_gaming_official_ff_data-2.3.9.dist-info/top_level.txt
hl_gaming_official_ff_data-2.3.9.dist-info/RECORD
