Metadata-Version: 2.4
Name: hl_gaming_official_ff_data
Version: 2.3.9
Summary: Python client for HL Gaming Official Free Fire API
Home-page: https://www.hlgamingofficial.com/p/api.html
Author: Haroon Brokha
Author-email: developers@hlgamingofficial.com
License: MIT
Project-URL: Documentation, https://www.hlgamingofficial.com/p/free-fire-account-information-python.html
Project-URL: Homepage, https://www.hlgamingofficial.com
Project-URL: Contact, https://www.hlgamingofficial.com/p/contact-us.html
Project-URL: Feedback, https://www.hlgamingofficial.com/p/feedback.html
Classifier: Programming Language :: Python :: 3
Classifier: Programming Language :: Python :: 3.8
Classifier: Programming Language :: Python :: 3.9
Classifier: Programming Language :: Python :: 3.10
Classifier: Operating System :: OS Independent
Classifier: License :: OSI Approved :: MIT License
Classifier: Topic :: Software Development :: Libraries :: Python Modules
Requires-Python: >=3.8
Requires-Dist: requests>=2.28.0
Provides-Extra: cache
Requires-Dist: cachetools>=5.0.0; extra == "cache"
Dynamic: author
Dynamic: author-email
Dynamic: classifier
Dynamic: description
Dynamic: description-content-type
Dynamic: home-page
Dynamic: license
Dynamic: project-url
Dynamic: provides-extra
Dynamic: requires-dist
Dynamic: requires-python
Dynamic: summary
